youtube_download_transcription/__init__.py
youtube_download_transcription/main.py
youtube_download_transcription-3.0.dist-info/METADATA
youtube_download_transcription-3.0.dist-info/WHEEL
youtube_download_transcription-3.0.dist-info/top_level.txt
youtube_download_transcription-3.0.dist-info/RECORD
