Metadata-Version: 2.1
Name: youtube_download_transcription
Version: 3.0
Author: Ciorobitca Mihai
Requires-Dist: selenium
